rapiduino/__init__.py
rapiduino/boards/__init__.py
rapiduino/boards/arduino.py
rapiduino/boards/pins.py
rapiduino/communication/__init__.py
rapiduino/communication/command_spec.py
rapiduino/communication/serial.py
rapiduino/components/__init__.py
rapiduino/components/base.py
rapiduino/components/led.py
rapiduino/exceptions.py
rapiduino/globals/__init__.py
rapiduino/globals/arduino_mega_2560.py
rapiduino/globals/arduino_uno.py
rapiduino/globals/common.py
rapiduino-1.2.0.dist-info/LICENSE
rapiduino-1.2.0.dist-info/WHEEL
rapiduino-1.2.0.dist-info/METADATA
rapiduino-1.2.0.dist-info/RECORD
