Metadata-Version: 2.1
Name: rapiduino
Version: 1.2.0
Summary: Rapidly develop code to control an Arduino using Python
License: Apache-2.0
Author: Sam Wedge
Author-email: sam.wedge@gmail.com
Requires-Python: >=3.6.1,<4.0.0
Classifier: License :: OSI Approved :: Apache Software License
Classifier: Programming Language :: Python :: 3
Classifier: Programming Language :: Python :: 3.7
Classifier: Programming Language :: Python :: 3.8
Classifier: Programming Language :: Python :: 3.9
Requires-Dist: dataclasses (>=0.8,<0.9); python_version >= "3.6" and python_version < "3.7"
Requires-Dist: pyserial (>=3.5,<4.0)
